MANIFEST.in
README.rst
setup.py
FortuneCookie.egg-info/PKG-INFO
FortuneCookie.egg-info/SOURCES.txt
FortuneCookie.egg-info/dependency_links.txt
FortuneCookie.egg-info/not-zip-safe
FortuneCookie.egg-info/top_level.txt
fortune_cookie/__init__.py
fortune_cookie/cookie.py
fortune_cookie/phrases.txt