Metadata-Version: 1.0
Name: FortuneCookie
Version: 0.2
Summary: A Python package for fortune cookie phrases generation
Home-page: https://github.com/carrasquel/fortune-cookie
Author: Nelson Carrasquel
Author-email: carrasquel.nelson@gmail.com
License: Apache License
Platform: UNKNOWN
